mlflow/__init__.py
mlflow/_spark_autologging.py
mlflow/cli.py
mlflow/data.py
mlflow/db.py
mlflow/exceptions.py
mlflow/experiments.py
mlflow/gluon.py
mlflow/h2o.py
mlflow/keras.py
mlflow/lightgbm.py
mlflow/mleap.py
mlflow/onnx.py
mlflow/runs.py
mlflow/sklearn.py
mlflow/spark.py
mlflow/tensorflow.py
mlflow/transformers.py
mlflow/version.py
mlflow/xgboost.py
mlflow/azureml/__init__.py
mlflow/azureml/cli.py
mlflow/entities/__init__.py
mlflow/entities/_mlflow_object.py
mlflow/entities/experiment.py
mlflow/entities/experiment_tag.py
mlflow/entities/file_info.py
mlflow/entities/lifecycle_stage.py
mlflow/entities/metric.py
mlflow/entities/param.py
mlflow/entities/run.py
mlflow/entities/run_data.py
mlflow/entities/run_info.py
mlflow/entities/run_status.py
mlflow/entities/run_tag.py
mlflow/entities/source_type.py
mlflow/entities/view_type.py
mlflow/entities/model_registry/__init__.py
mlflow/entities/model_registry/_model_registry_entity.py
mlflow/entities/model_registry/model_version.py
mlflow/entities/model_registry/model_version_detailed.py
mlflow/entities/model_registry/model_version_stages.py
mlflow/entities/model_registry/model_version_status.py
mlflow/entities/model_registry/registered_model.py
mlflow/entities/model_registry/registered_model_detailed.py
mlflow/models/__init__.py
mlflow/models/cli.py
mlflow/models/docker_utils.py
mlflow/models/flavor_backend_registry.py
mlflow/models/original__init__.py
mlflow/models/container/__init__.py
mlflow/models/container/scoring_server/__init__.py
mlflow/models/container/scoring_server/nginx.conf
mlflow/models/container/scoring_server/wsgi.py
mlflow/projects/__init__.py
mlflow/projects/_project_spec.py
mlflow/projects/databricks.py
mlflow/projects/kubernetes.py
mlflow/projects/submitted_run.py
mlflow/projects/utils.py
mlflow/protos/__init__.py
mlflow/protos/databricks_pb2.py
mlflow/protos/model_registry_pb2.py
mlflow/protos/service_pb2.py
mlflow/protos/scalapb/__init__.py
mlflow/protos/scalapb/scalapb_pb2.py
jliang_mlflow_transformers_flavor-1.5.1.dev0.dist-info/LICENSE.txt
jliang_mlflow_transformers_flavor-1.5.1.dev0.dist-info/METADATA
jliang_mlflow_transformers_flavor-1.5.1.dev0.dist-info/WHEEL
jliang_mlflow_transformers_flavor-1.5.1.dev0.dist-info/entry_points.txt
jliang_mlflow_transformers_flavor-1.5.1.dev0.dist-info/top_level.txt
jliang_mlflow_transformers_flavor-1.5.1.dev0.dist-info/RECORD
