Metadata-Version: 2.1
Name: jliang-mlflow-transformers-flavor
Version: 1.5.1.dev0
Summary: MLflow with Transformers custom flavor
Home-page: https://github.pie.apple.com/jason-liang4/MLFlow-Transformers-Custom-Flavor
Author: Jason Liang
License: Apache License 2.0
Keywords: ml ai transformers serving
Platform: UNKNOWN
Classifier: Intended Audience :: Developers
Classifier: Programming Language :: Python :: 2.7
Classifier: Programming Language :: Python :: 3.6
Requires-Dist: alembic
Requires-Dist: click (>=7.0)
Requires-Dist: cloudpickle
Requires-Dist: databricks-cli (>=0.8.7)
Requires-Dist: requests (>=2.17.3)
Requires-Dist: six (>=1.10.0)
Requires-Dist: Flask
Requires-Dist: numpy
Requires-Dist: pandas
Requires-Dist: python-dateutil
Requires-Dist: protobuf (>=3.6.0)
Requires-Dist: gitpython (>=2.1.0)
Requires-Dist: pyyaml
Requires-Dist: querystring-parser
Requires-Dist: simplejson
Requires-Dist: docker (>=4.0.0)
Requires-Dist: entrypoints
Requires-Dist: sqlparse
Requires-Dist: sqlalchemy
Requires-Dist: gorilla
Requires-Dist: prometheus-flask-exporter
Requires-Dist: transformers
Requires-Dist: gunicorn ; platform_system != "Windows"
Requires-Dist: waitress ; platform_system == "Windows"
Provides-Extra: extras
Requires-Dist: boto3 (>=1.7.12) ; extra == 'extras'
Requires-Dist: mleap (>=0.8.1) ; extra == 'extras'
Requires-Dist: azure-storage ; extra == 'extras'
Requires-Dist: google-cloud-storage ; extra == 'extras'
Requires-Dist: scikit-learn (==0.20) ; (python_version < "3.5") and extra == 'extras'
Requires-Dist: scikit-learn ; (python_version >= "3.5") and extra == 'extras'
Provides-Extra: sqlserver
Requires-Dist: mlflow-dbstore ; extra == 'sqlserver'
